README.md
setup.py
yuanxin/__init__.py
yuanxin.egg-info/PKG-INFO
yuanxin.egg-info/SOURCES.txt
yuanxin.egg-info/dependency_links.txt
yuanxin.egg-info/top_level.txt