Metadata-Version: 2.1
Name: yuanxin
Version: 0.1.5
Summary: yuanxin-sdk
Home-page: UNKNOWN
Author: assassin
Author-email: assassin@pypi.org
License: UNKNOWN
Platform: UNKNOWN
Classifier: Programming Language :: Python :: 3
Classifier: License :: OSI Approved :: MIT License
Classifier: Operating System :: OS Independent
Requires-Python: >=3.6
